src/__init__.py
src/cmd.py
src/pkg/config.py
src/pkg/users.py
src/pkg/utils.py
dtaas-0.1.1.dist-info/METADATA
dtaas-0.1.1.dist-info/WHEEL
dtaas-0.1.1.dist-info/entry_points.txt
dtaas-0.1.1.dist-info/RECORD
